week7/q2b.v
module mux2to1(w0,w1,s,f);
	input w0,w1,s;
	output reg f;
	always@(w0 or w1 or s)
	begin
		if(s==0)
			f=w0;
		else
			f=w1;
	end
endmodule

module q2b(w1,w2,w3,f);
	input w1,w2,w3;
	output f;
	wire g,h;
	mux2to1 stage0(1'b0,w3,w2,g);
	mux2to1 stage1(w3,1'b1,w2,h);
	mux2to1 stage2(g,h,w1,f);
endmodule

week7/q2b_tb.v
`timescale 1ns/1ns
`include "q2b.v"

module q2b_tb();
reg w1,w2,w3;
wire f;

q2b ex(w1,w2,w3,f);
initial
begin
	$dumpfile("q2b_tb.vcd");
	$dumpvars(0,q2b_tb);
	w1=1'b0;w2=1'b0;w3=1'b0;
	#20;
	
	w1=1'b0;w2=1'b0;w3=1'b1;
	#20;
	
	w1=1'b0;w2=1'b1;w3=1'b0;
	#20;
	
	w1=1'b0;w2=1'b1;w3=1'b1;
	#20;
	
	w1=1'b1;w2=1'b0;w3=1'b0;
	#20;
	
	w1=1'b1;w2=1'b0;w3=1'b1;
	#20;
	
	w1=1'b1;w2=1'b1;w3=1'b0;
	#20;
	
	w1=1'b1;w2=1'b1;w3=1'b1;
	#20;
	
	$display("Test complete");
	
end
endmodule

week7/q2b_tb.vcd
$date
	Mon Oct 17 09:44:48 2022
$end
$version
	Icarus Verilog
$end
$timescale
	1ns
$end
$scope module q2b_tb $end
$var wire 1 ! f $end
$var reg 1 " w1 $end
$var reg 1 # w2 $end
$var reg 1 $ w3 $end
$scope module ex $end
$var wire 1 " w1 $end
$var wire 1 # w2 $end
$var wire 1 $ w3 $end
$var wire 1 % h $end
$var wire 1 & g $end
$var wire 1 ! f $end
$scope module stage0 $end
$var wire 1 # s $end
$var wire 1 ' w0 $end
$var wire 1 $ w1 $end
$var reg 1 & f $end
$upscope $end
$scope module stage1 $end
$var wire 1 # s $end
$var wire 1 $ w0 $end
$var wire 1 ( w1 $end
$var reg 1 % f $end
$upscope $end
$scope module stage2 $end
$var wire 1 " s $end
$var wire 1 & w0 $end
$var wire 1 % w1 $end
$var reg 1 ! f $end
$upscope $end
$upscope $end
$upscope $end
$enddefinitions $end
#0
$dumpvars
1(
0'
0&
0%
0$
0#
0"
0!
$end
#20
1%
1$
#40
0$
1#
#60
1!
1&
1$
#80
0!
0&
0%
0$
0#
1"
#100
1!
1%
1$
#120
0$
1#
#140
1&
1$
