week7/q3.v
module mux8to1(w0,w1,w2,w3,w4,w5,w6,w7,S0,S1,S2,f);
	input w0,w1,w2,w3,w4,w5,w6,w7,S0,S1,S2;
	output reg f;
	always@(w0 or w1 or w2 or w3 or w4 or w5 or w6 or w7 or S0 or S1 or S2)
	begin
		if(S2==0 & S1==0 & S0==0)
			assign f=w0;
		if(S2==0 & S1==0 & S0==1)
			assign f=w1;
		if(S2==0 & S1==1 & S0==0)
			assign f=w2;
		if(S2==0 & S1==1 & S0==1)
			assign f=w3;
		if(S2==1 & S1==0 & S0==0)
			assign f=w4;
		if(S2==1 & S1==0 & S0==1)
			assign f=w5;
		if(S2==1 & S1==1 & S0==0)
			assign f=w6;
		if(S2==1 & S1==1 & S0==1)
			assign f=w7;
	end
endmodule

module q3(B0,B1,B2,B3,E0,E1,E2,E3);
	input B0,B1,B2,B3;
	output E0,E1,E2,E3;
	assign E0=~B0;
	mux8to1 stage0(~B0,B0,~B0,B0,~B0,1'b0,1'b0,1'b0,B1,B2,B3,E1);
	mux8to1 stage1(B0,1'b1,~B0,1'b0,B0,1'b0,1'b0,1'b0,B1,B2,B3,E2);
	mux8to1 stage2(1'b0,1'b0,B0,1'b1,1'b1,1'b0,1'b0,1'b0,B1,B2,B3,E3);
endmodule

week7/q3_tb.v
`timescale 1ns/1ns
`include "q3.v"

module q3_tb();
reg B0,B1,B2,B3;
wire E0,E1,E2,E3;

q3 ex1(B0,B1,B2,B3,E0,E1,E2,E3);
initial
begin
	$dumpfile("q3_tb.vcd");
	$dumpvars(0,q3_tb);
	B0=1'b0; B1=1'b0; B2=1'b0; B3=1'b0;
	#20;
	
	B0=1'b1; B1=1'b0; B2=1'b0; B3=1'b0;
	#20;
	
	B0=1'b0; B1=1'b1; B2=1'b0; B3=1'b0;
	#20;
	
	B0=1'b1; B1=1'b1; B2=1'b0; B3=1'b0;
	#20;
	
	B0=1'b0; B1=1'b0; B2=1'b1; B3=1'b0;
	#20;
	
	B0=1'b1; B1=1'b0; B2=1'b1; B3=1'b0;
	#20;
	
	B0=1'b0; B1=1'b1; B2=1'b1; B3=1'b0;
	#20;
	
	B0=1'b1; B1=1'b1; B2=1'b1; B3=1'b0;
	#20;
	
	B0=1'b0; B1=1'b0; B2=1'b0; B3=1'b1;
	#20;
	
	B0=1'b1; B1=1'b0; B2=1'b0; B3=1'b1;
	#20;
	
	$display("Test complete");
end
endmodule

week7/q3_tb.vcd
$date
	Mon Oct 10 11:17:11 2022
$end
$version
	Icarus Verilog
$end
$timescale
	1ns
$end
$scope module q3_tb $end
$var wire 1 ! E3 $end
$var wire 1 " E2 $end
$var wire 1 # E1 $end
$var wire 1 $ E0 $end
$var reg 1 % B0 $end
$var reg 1 & B1 $end
$var reg 1 ' B2 $end
$var reg 1 ( B3 $end
$scope module ex1 $end
$var wire 1 % B0 $end
$var wire 1 & B1 $end
$var wire 1 ' B2 $end
$var wire 1 ( B3 $end
$var wire 1 $ E0 $end
$var wire 1 ! E3 $end
$var wire 1 " E2 $end
$var wire 1 # E1 $end
$scope module stage0 $end
$var wire 1 & S0 $end
$var wire 1 ' S1 $end
$var wire 1 ( S2 $end
$var wire 1 ) w0 $end
$var wire 1 % w1 $end
$var wire 1 * w2 $end
$var wire 1 % w3 $end
$var wire 1 + w4 $end
$var wire 1 , w5 $end
$var wire 1 - w6 $end
$var wire 1 . w7 $end
$var reg 1 # f $end
$upscope $end
$scope module stage1 $end
$var wire 1 & S0 $end
$var wire 1 ' S1 $end
$var wire 1 ( S2 $end
$var wire 1 % w0 $end
$var wire 1 / w1 $end
$var wire 1 0 w2 $end
$var wire 1 1 w3 $end
$var wire 1 % w4 $end
$var wire 1 2 w5 $end
$var wire 1 3 w6 $end
$var wire 1 4 w7 $end
$var reg 1 " f $end
$upscope $end
$scope module stage2 $end
$var wire 1 & S0 $end
$var wire 1 ' S1 $end
$var wire 1 ( S2 $end
$var wire 1 5 w0 $end
$var wire 1 6 w1 $end
$var wire 1 % w2 $end
$var wire 1 7 w3 $end
$var wire 1 8 w4 $end
$var wire 1 9 w5 $end
$var wire 1 : w6 $end
$var wire 1 ; w7 $end
$var reg 1 ! f $end
$upscope $end
$upscope $end
$upscope $end
$enddefinitions $end
#0
$dumpvars
0;
0:
09
18
17
06
05
04
03
02
01
10
1/
0.
0-
0,
1+
1*
1)
0(
0'
0&
0%
1$
1#
0"
0!
$end
#20
0$
0#
0)
0*
0+
00
1"
1%
#40
1$
1)
1*
1+
10
1&
1"
0%
#60
0$
0)
0*
0+
00
1#
1%
#80
1$
1)
1*
1+
10
1"
1'
0&
1#
0%
#100
0$
0)
0#
0*
0+
0"
00
1!
1%
#120
1$
1)
1*
1+
10
1&
1!
0%
#140
0$
0)
0*
0+
00
1#
1%
#160
1$
1)
1*
1+
10
1(
0'
0&
1#
0%
#180
0$
0)
0*
0#
0+
00
1"
1%
