week7/q4.v
module mux4to1(w,s,f);
	input [3:0]w;
	input [1:0]s;
	output reg f;
	always@(w or s)
	begin
		f=s[1]?(s[0]?w[3]:w[2]):(s[0]?w[1]:w[0]);
	end
endmodule

module q4(B,G);
	input [3:0]B;
	output [3:0]G;
	wire [3:0]w0,w1,w2,w3;
	assign i=B[3]^B[2];
	
	assign w0={1'b0,1'b1,1'b1,1'b0};
	assign w1={~B[2],~B[2],B[2],B[2]};
	assign w2={i,i,i,i};
	assign w3={B[3],B[3],B[3],B[3]};
	
	mux4to1 stage0(w0,B[1:0],G[0]);
	mux4to1 stage1(w1,B[1:0],G[1]);
	mux4to1 stage2(w2,B[1:0],G[2]);
	mux4to1 stage3(w3,B[1:0],G[3]);
endmodule

week7/q4_tb.v
`timescale 1ns/1ns
`include "q4.v"

module q4_tb();
reg [3:0]B;
wire [3:0]G;

q4 ex(B,G);
initial 
begin
	$dumpfile("q4_tb.vcd");
	$dumpvars(0,q4_tb);
	B=0;
	#20;
	
	B=1;
	#20;
	
	B=2;
	#20;
	
	B=3;
	#20;
	
	B=4;
	#20;
	
	B=5;
	#20;
	
	B=6;
	#20;
	
	B=7;
	#20;
	
	B=8;
	#20;
	
	B=9;
	#20;
	
	B=10;
	#20;
	
	B=11;
	#20;
	
	B=12;
	#20;
	
	B=13;
	#20;
	
	B=14;
	#20;
	
	B=15;
	#20;
	
	$display("Test complete");
end
endmodule

week7/q4_tb.vcd
$date
	Mon Oct 17 09:57:13 2022
$end
$version
	Icarus Verilog
$end
$timescale
	1ns
$end
$scope module q4_tb $end
$var wire 4 ! G [3:0] $end
$var reg 4 " B [3:0] $end
$scope module ex $end
$var wire 4 # B [3:0] $end
$var wire 1 $ i $end
$var wire 4 % w0 [3:0] $end
$var wire 4 & w3 [3:0] $end
$var wire 4 ' w2 [3:0] $end
$var wire 4 ( w1 [3:0] $end
$var wire 4 ) G [3:0] $end
$scope module stage0 $end
$var wire 2 * s [1:0] $end
$var wire 4 + w [3:0] $end
$var reg 1 , f $end
$upscope $end
$scope module stage1 $end
$var wire 2 - s [1:0] $end
$var wire 4 . w [3:0] $end
$var reg 1 / f $end
$upscope $end
$scope module stage2 $end
$var wire 2 0 s [1:0] $end
$var wire 4 1 w [3:0] $end
$var reg 1 2 f $end
$upscope $end
$scope module stage3 $end
$var wire 2 3 s [1:0] $end
$var wire 4 4 w [3:0] $end
$var reg 1 5 f $end
$upscope $end
$upscope $end
$upscope $end
$enddefinitions $end
#0
$dumpvars
05
b0 4
b0 3
02
b0 1
b0 0
0/
b1100 .
b0 -
0,
b110 +
b0 *
b0 )
b1100 (
b0 '
b0 &
b110 %
0$
b0 #
b0 "
b0 !
$end
#20
b1 !
b1 )
1,
b1 *
b1 -
b1 0
b1 3
b1 "
b1 #
#40
b11 !
b11 )
1/
b10 *
b10 -
b10 0
b10 3
b10 "
b10 #
#60
b10 !
b10 )
0,
b11 *
b11 -
b11 0
b11 3
b11 "
b11 #
#80
b110 !
b110 )
12
b1111 '
b1111 1
1$
b11 (
b11 .
b0 *
b0 -
b0 0
b0 3
b100 "
b100 #
#100
b111 !
b111 )
1,
b1 *
b1 -
b1 0
b1 3
b101 "
b101 #
#120
b101 !
b101 )
0/
b10 *
b10 -
b10 0
b10 3
b110 "
b110 #
#140
b100 !
b100 )
0,
b11 *
b11 -
b11 0
b11 3
b111 "
b111 #
#160
b1100 !
b1100 )
15
b1100 (
b1100 .
b1111 &
b1111 4
b0 *
b0 -
b0 0
b0 3
b1000 "
b1000 #
#180
b1101 !
b1101 )
1,
b1 *
b1 -
b1 0
b1 3
b1001 "
b1001 #
#200
b1111 !
b1111 )
1/
b10 *
b10 -
b10 0
b10 3
b1010 "
b1010 #
#220
b1110 !
b1110 )
0,
b11 *
b11 -
b11 0
b11 3
b1011 "
b1011 #
#240
b1010 !
b1010 )
02
b0 '
b0 1
0$
b11 (
b11 .
b0 *
b0 -
b0 0
b0 3
b1100 "
b1100 #
#260
b1011 !
b1011 )
1,
b1 *
b1 -
b1 0
b1 3
b1101 "
b1101 #
#280
b1001 !
b1001 )
0/
b10 *
b10 -
b10 0
b10 3
b1110 "
b1110 #
#300
b1000 !
b1000 )
0,
b11 *
b11 -
b11 0
b11 3
b1111 "
b1111 #
