week7/ques1a.v
module mux8to1(w,s,f);
	input [7:0]w;
	input [2:0]s;
	output reg f;
	always@(w or s)
	begin 
		case(s)
			0:f=w[0];
			1:f=w[1];
			2:f=w[2];
			3:f=w[3];
			4:f=w[4];
			5:f=w[5];
			6:f=w[6];
			7:f=w[7];
		endcase
	end
endmodule

module ques1a(a,b,c,d,f);
	input a,b,c,d;
	output f;
	wire [7:0]w;
	wire [2:0]s;
	
	assign w={~d,1'b1,1'b0,1'b1,1'b1,1'b1,1'b0,1'b0};
	assign s={a,b,c};
	
	mux8to1 stage0(w,s,f);
endmodule

week7/ques1a_tb.v
`timescale 1ns/1ns
`include "ques1a.v"

module ques1a_tb();
reg a,b,c,d;
wire f;

ques1a ex1(a,b,c,d,f);
initial
begin
	$dumpfile("ques1a_tb.vcd");
	$dumpvars(0,ques1a_tb);
	a=1'b0; b=1'b0; c=1'b0; d=1'b0;
	#20;
	
	a=1'b0; b=1'b0; c=1'b0; d=1'b1;
	#20;
	
	a=1'b0; b=1'b0; c=1'b1; d=1'b0;
	#20;
	
	a=1'b0; b=1'b0; c=1'b1; d=1'b1;
	#20;
	
	a=1'b0; b=1'b1; c=1'b0; d=1'b0;
	#20;
	
	a=1'b0; b=1'b1; c=1'b0; d=1'b1;
	#20;
	
	a=1'b0; b=1'b1; c=1'b1; d=1'b0;
	#20;
	
	a=1'b0; b=1'b1; c=1'b1; d=1'b1;
	#20;
	
	a=1'b1; b=1'b0; c=1'b0; d=1'b0;
	#20;
	
	a=1'b1; b=1'b0; c=1'b0; d=1'b1;
	#20;
	
	a=1'b1; b=1'b0; c=1'b1; d=1'b0;
	#20;
	
	a=1'b1; b=1'b0; c=1'b1; d=1'b1;
	#20;
	
	a=1'b1; b=1'b1; c=1'b0; d=1'b0;
	#20;
	
	a=1'b1; b=1'b1; c=1'b0; d=1'b1;
	#20;
	
	a=1'b1; b=1'b1; c=1'b1; d=1'b0;
	#20;
	
	a=1'b1; b=1'b1; c=1'b1; d=1'b1;
	#20;
	
	$display("Test complete");
end
endmodule

week7/ques1a_tb.vcd
$date
	Mon Oct 17 09:24:31 2022
$end
$version
	Icarus Verilog
$end
$timescale
	1ns
$end
$scope module ques1a_tb $end
$var wire 1 ! f $end
$var reg 1 " a $end
$var reg 1 # b $end
$var reg 1 $ c $end
$var reg 1 % d $end
$scope module ex1 $end
$var wire 1 " a $end
$var wire 1 # b $end
$var wire 1 $ c $end
$var wire 1 % d $end
$var wire 8 & w [7:0] $end
$var wire 3 ' s [2:0] $end
$var wire 1 ! f $end
$scope module stage0 $end
$var wire 3 ( s [2:0] $end
$var wire 8 ) w [7:0] $end
$var reg 1 ! f $end
$upscope $end
$upscope $end
$upscope $end
$enddefinitions $end
#0
$dumpvars
b11011100 )
b0 (
b0 '
b11011100 &
0%
0$
0#
0"
0!
$end
#20
b1011100 &
b1011100 )
1%
#40
b11011100 &
b11011100 )
0%
b1 '
b1 (
1$
#60
b1011100 &
b1011100 )
1%
#80
b11011100 &
b11011100 )
1!
0%
0$
b10 '
b10 (
1#
#100
b1011100 &
b1011100 )
1%
#120
b11011100 &
b11011100 )
0%
b11 '
b11 (
1$
#140
b1011100 &
b1011100 )
1%
#160
b11011100 &
b11011100 )
0%
0$
0#
b100 '
b100 (
1"
#180
b1011100 &
b1011100 )
1%
#200
b11011100 &
b11011100 )
0!
0%
b101 '
b101 (
1$
#220
b1011100 &
b1011100 )
1%
#240
b11011100 &
b11011100 )
1!
0%
0$
b110 '
b110 (
1#
#260
b1011100 &
b1011100 )
1%
#280
b11011100 &
b11011100 )
1!
0%
b111 '
b111 (
1$
#300
0!
b1011100 &
b1011100 )
1%
