week1/lab1_q2.v
module lab1_q2(a,b,c,d,f,g);
  input a,b,c,d;
  output f,g;
  nand (h,a,b );
  xor (f, d,g,c);
  nor (g, h,c,b);
 endmodule

lab1_q2_tb.v
`timescale 1ns/1ns
`include "lab1_q2.v"

module lab1_q2_tb();
reg a,b,c,d;
wire f;

lab1_q2 l1(a,b,c,d,f,g);
initial
begin

  $dumpfile("lab1_q2_tb.vcd");
  $dumpvars(0, lab1_q2_tb);
  
  a=1'b0; b=1'b0; c=1'b0; d=1'b0;
  #20;
  
  a=1'b0; b=1'b0; c=1'b0; d=1'b1;
  #20;
  
  a=1'b0; b=1'b0; c=1'b1; d=1'b0;
  #20;
  
  a=1'b0; b=1'b0; c=1'b1; d=1'b1;
  #20;
  
  a=1'b0; b=1'b1; c=1'b0; d=1'b0;
  #20;
  
  a=1'b0; b=1'b1; c=1'b0; d=1'b1;
  #20;
  
  a=1'b0; b=1'b1; c=1'b1; d=1'b0;
  #20;
  
  a=1'b0; b=1'b1; c=1'b1; d=1'b1;
  #20;
  
  a=1'b0; b=1'b0; c=1'b0; d=1'b0;
  #20;
  
  a=1'b0; b=1'b0; c=1'b0; d=1'b1;
  #20;
  
  a=1'b0; b=1'b0; c=1'b1; d=1'b0;
  #20;
  
  a=1'b0; b=1'b0; c=1'b1; d=1'b1;
  #20;
  
  a=1'b1; b=1'b1; c=1'b0; d=1'b0;
  #20;
  
  a=1'b1; b=1'b1; c=1'b0; d=1'b1;
  #20;
  
  a=1'b1; b=1'b1; c=1'b1; d=1'b0;
  #20;
  
  a=1'b1; b=1'b1; c=1'b1; d=1'b1;
  #20;
  
 a=1'b1; b=1'b0; c=1'b0; d=1'b0;
  #20;
  
  a=1'b1; b=1'b0; c=1'b0; d=1'b1;
  #20;
  
  a=1'b1; b=1'b0; c=1'b1; d=1'b0;
  #20;
  
  a=1'b1; b=1'b0; c=1'b1; d=1'b1;
  #20;
  
 
  
 
 
  
  $display("test complete");
end 

endmodule

lab1_q2_tb.vcd
$date
	Mon Aug 22 11:18:43 2022
$end
$version
	Icarus Verilog
$end
$timescale
	1ns
$end
$scope module lab1_q2_tb $end
$var wire 1 ! g $end
$var wire 1 " f $end
$var reg 1 # a $end
$var reg 1 $ b $end
$var reg 1 % c $end
$var reg 1 & d $end
$scope module l1 $end
$var wire 1 # a $end
$var wire 1 $ b $end
$var wire 1 % c $end
$var wire 1 & d $end
$var wire 1 " f $end
$var wire 1 ! g $end
$var wire 1 ' h $end
$upscope $end
$upscope $end
$enddefinitions $end
#0
$dumpvars
1'
0&
0%
0$
0#
0"
0!
$end
#20
1"
1&
#40
0&
1%
#60
0"
1&
#80
0&
0%
1$
#100
1"
1&
#120
0&
1%
#140
0"
1&
#160
0&
0%
0$
#180
1"
1&
#200
0&
1%
#220
0"
1&
#240
0'
0&
0%
1$
1#
#260
1"
1&
#280
0&
1%
#300
0"
1&
#320
0"
1'
0!
0&
0%
0$
#340
1"
1&
#360
0&
1%
#380
0"
1&
