week6/mux16to1_8.v
module mux8to1(w,s,f);
input [7:0]w;
input [2:0]s;
output f;
reg f;
always @(w or s)
case(s)
0:f=w[0];
1:f=w[1];
2:f=w[2];
3:f=w[3];
4:f=w[4];
5:f=w[5];
6:f=w[6];
7:f=w[7];
endcase
endmodule
module mux2to1(w,s,f);
input [1:0]w;
input s;
output f;
reg f;
always @(w[0] or w[1] or s)
if (s==0)
f=w[0];
else
f=w[1];
endmodule


module mux16to1_8(w,s,f);
input [15:0]w;
input [3:0]s;
output f;
wire [1:0]i;
mux8to1 stg0(w[7:0],s[2:0],i[0]);
mux8to1 stg1(w[15:8],s[2:0],i[1]);
mux2to1 stg2(i[1:0],s[3],f);
endmodule

week6/mux16to1_8_tb.v
`timescale 1ns/1ns
`include "mux16to1_8.v"
module mux16to1_8_tb();
reg [15:0]w;
reg [3:0]s;
wire f;
mux16to1_8 ques3(w,s,f);
initial
begin
	$dumpfile("mux16to1_8_tb.vcd");
	$dumpvars(0,mux16to1_8_tb);
	s=0;w=30;
	#20;
	s=1;w=30;
	#20;
	s=2;w=30;
	#20;
	s=3;w=30;
	#20;
	s=4;w=30;
	#20;
	s=5;w=30;
	#20;
	s=6;w=30;
	#20;
	s=7;w=30;
	#20;
	s=8;w=30;
	#20;
	s=9;w=30;
	#20;
	s=10;w=30;
	#20;
	s=11;w=30;
	#20;
	s=12;w=30;
	#20;
	s=13;w=30;
	#20;
	s=14;w=30;
	#20;
	s=15;w=30;
	#20;
	$display("test complete");
	end
endmodule

week6/mux16to1_8_tb.vcd
$date
	Mon Oct  3 10:40:11 2022
$end
$version
	Icarus Verilog
$end
$timescale
	1ns
$end
$scope module mux16to1_8_tb $end
$var wire 1 ! f $end
$var reg 4 " s [3:0] $end
$var reg 16 # w [15:0] $end
$scope module ques3 $end
$var wire 4 $ s [3:0] $end
$var wire 16 % w [15:0] $end
$var wire 2 & i [1:0] $end
$var wire 1 ! f $end
$scope module stg0 $end
$var wire 3 ' s [2:0] $end
$var wire 8 ( w [7:0] $end
$var reg 1 ) f $end
$upscope $end
$scope module stg1 $end
$var wire 3 * s [2:0] $end
$var wire 8 + w [7:0] $end
$var reg 1 , f $end
$upscope $end
$scope module stg2 $end
$var wire 1 - s $end
$var wire 2 . w [1:0] $end
$var reg 1 ! f $end
$upscope $end
$upscope $end
$upscope $end
$enddefinitions $end
#0
$dumpvars
b0 .
0-
0,
b0 +
b0 *
0)
b11110 (
b0 '
b0 &
b11110 %
b0 $
b11110 #
b0 "
0!
$end
#20
1!
b1 &
b1 .
1)
b1 '
b1 *
b1 "
b1 $
#40
b10 '
b10 *
b10 "
b10 $
#60
b11 '
b11 *
b11 "
b11 $
#80
b100 '
b100 *
b100 "
b100 $
#100
0!
b0 &
b0 .
0)
b101 '
b101 *
b101 "
b101 $
#120
b110 '
b110 *
b110 "
b110 $
#140
b111 '
b111 *
b111 "
b111 $
#160
b0 '
b0 *
1-
b1000 "
b1000 $
#180
b1 &
b1 .
1)
b1 '
b1 *
b1001 "
b1001 $
#200
b10 '
b10 *
b1010 "
b1010 $
#220
b11 '
b11 *
b1011 "
b1011 $
#240
b100 '
b100 *
b1100 "
b1100 $
#260
b0 &
b0 .
0)
b101 '
b101 *
b1101 "
b1101 $
#280
b110 '
b110 *
b1110 "
b1110 $
#300
b111 '
b111 *
b1111 "
b1111 $
