week6/mux16to1.v
module mux4to1(w,s,f);
input [3:0]w;
input [1:0]s;
output f;
assign f=s[1]?(s[0]?w[3]:w[2]):(s[0]?w[1]:w[0]);
endmodule

module mux16to1(w,s,f);
input [15:0]w;
input [3:0]s;
output f;
wire [3:0]i;
mux4to1 stg0(w[3:0],s[1:0],i[0]);
mux4to1 stg1(w[7:4],s[1:0],i[1]);
mux4to1 stg2(w[11:8],s[1:0],i[2]);
mux4to1 stg3(w[15:12],s[1:0],i[3]);
mux4to1 stg4(i[3:0],s[3:2],f);
endmodule

week6/mux16to1_tb.v
`timescale 1ns/1ns
`include "mux16to1.v"
module mux16to1_tb();
reg [15:0]w;
reg [3:0]s;
wire f;
mux16to1 ques2(w,s,f);
initial
begin
	$dumpfile("mux16to1_tb.vcd");
	$dumpvars(0,mux16to1_tb);
	s=0;w=25;
	#20;
	s=1;w=25;
	#20;
	s=2;w=25;
	#20;
	s=3;w=25;
	#20;
	s=4;w=25;
	#20;
	s=5;w=25;
	#20;
	s=6;w=25;
	#20;
	s=7;w=25;
	#20;
	s=8;w=25;
	#20;
	s=9;w=25;
	#20;
	s=10;w=25;
	#20;
	s=11;w=25;
	#20;
	s=12;w=25;
	#20;
	s=13;w=25;
	#20;
	s=14;w=25;
	#20;
	s=15;w=25;
	#20;
	$display("test complete");
	end
endmodule

week6/mux16to1_tb.vcd
$date
	Mon Oct  3 10:23:36 2022
$end
$version
	Icarus Verilog
$end
$timescale
	1ns
$end
$scope module mux16to1_tb $end
$var wire 1 ! f $end
$var reg 4 " s [3:0] $end
$var reg 16 # w [15:0] $end
$scope module ques2 $end
$var wire 4 $ s [3:0] $end
$var wire 16 % w [15:0] $end
$var wire 4 & i [3:0] $end
$var wire 1 ! f $end
$scope module stg0 $end
$var wire 2 ' s [1:0] $end
$var wire 4 ( w [3:0] $end
$var wire 1 ) f $end
$upscope $end
$scope module stg1 $end
$var wire 2 * s [1:0] $end
$var wire 4 + w [3:0] $end
$var wire 1 , f $end
$upscope $end
$scope module stg2 $end
$var wire 2 - s [1:0] $end
$var wire 4 . w [3:0] $end
$var wire 1 / f $end
$upscope $end
$scope module stg3 $end
$var wire 2 0 s [1:0] $end
$var wire 4 1 w [3:0] $end
$var wire 1 2 f $end
$upscope $end
$scope module stg4 $end
$var wire 2 3 s [1:0] $end
$var wire 4 4 w [3:0] $end
$var wire 1 ! f $end
$upscope $end
$upscope $end
$upscope $end
$enddefinitions $end
#0
$dumpvars
b11 4
b0 3
02
b0 1
b0 0
0/
b0 .
b0 -
1,
b1 +
b0 *
1)
b1001 (
b0 '
b11 &
b11001 %
b0 $
b11001 #
b0 "
1!
$end
#20
0!
0)
b0 &
b0 4
0,
b1 '
b1 *
b1 -
b1 0
b1 "
b1 $
#40
b10 '
b10 *
b10 -
b10 0
b10 "
b10 $
#60
1!
b1 &
b1 4
1)
b11 '
b11 *
b11 -
b11 0
b11 "
b11 $
#80
1!
b11 &
b11 4
1,
b0 '
b0 *
b0 -
b0 0
b1 3
b100 "
b100 $
#100
0!
0)
b0 &
b0 4
0,
b1 '
b1 *
b1 -
b1 0
b101 "
b101 $
#120
b10 '
b10 *
b10 -
b10 0
b110 "
b110 $
#140
b1 &
b1 4
1)
b11 '
b11 *
b11 -
b11 0
b111 "
b111 $
#160
b11 &
b11 4
1,
b0 '
b0 *
b0 -
b0 0
b10 3
b1000 "
b1000 $
#180
0)
b0 &
b0 4
0,
b1 '
b1 *
b1 -
b1 0
b1001 "
b1001 $
#200
b10 '
b10 *
b10 -
b10 0
b1010 "
b1010 $
#220
b1 &
b1 4
1)
b11 '
b11 *
b11 -
b11 0
b1011 "
b1011 $
#240
b11 &
b11 4
1,
b0 '
b0 *
b0 -
b0 0
b11 3
b1100 "
b1100 $
#260
0)
b0 &
b0 4
0,
b1 '
b1 *
b1 -
b1 0
b1101 "
b1101 $
#280
b10 '
b10 *
b10 -
b10 0
b1110 "
b1110 $
#300
b1 &
b1 4
1)
b11 '
b11 *
b11 -
b11 0
b1111 "
b1111 $
