week9/q3.v
module q3(w,En,f);
	input [2:0] w;
	input En;
	output f;
	wire [7:0] c;
	d24 s0(w[1:0],~w[2]&En,c[3:0]);
	d24 s1(w[1:0],w[2]&En,c[7:4]);
	assign f = c[3] | c[5] | c[6] | c[7];
endmodule


module d24(w,En,f);	
	input [1:0] w;
	input En;
	output reg [3:0] f;
	always@(w,En)
	begin
		case(En)
		  0: f = 4'b0000;
		  1:
		  begin
		  	case(w)
		  		0:f=4'b0001;
		  		1:f=4'b0010;
		  		2:f=4'b0100;
		  		3:f=4'b1000;
		  	endcase
		  end
		endcase
	end
endmodule

week9/q3_tb.v
`timescale 1ns/1ns
`include "q3.v"

module q3_tb();
reg [2:0] w;
reg En;
wire f;

q3 q3(w,En,f);
initial
begin
	$dumpfile("q3_tb.vcd");
	$dumpvars(0,q3_tb);
	
	En=1'b1;
	w=3'd0; #20;
	w=3'd1; #20;
	w=3'd2; #20;
	w=3'd3; #20;
	w=3'd4; #20;
	w=3'd5; #20;
	w=3'd6; #20;
	w=3'd7; #20;
	
	$display("Test Complete");
end 
endmodule

week9/q3_tb.vcd
$date
	Thu Oct 27 15:37:11 2022
$end
$version
	Icarus Verilog
$end
$timescale
	1ns
$end
$scope module q3_tb $end
$var wire 1 ! f $end
$var reg 1 " En $end
$var reg 3 # w [2:0] $end
$scope module q3 $end
$var wire 1 " En $end
$var wire 1 ! f $end
$var wire 3 $ w [2:0] $end
$var wire 8 % c [7:0] $end
$scope module s0 $end
$var wire 1 & En $end
$var wire 2 ' w [1:0] $end
$var reg 4 ( f [3:0] $end
$upscope $end
$scope module s1 $end
$var wire 1 ) En $end
$var wire 2 * w [1:0] $end
$var reg 4 + f [3:0] $end
$upscope $end
$upscope $end
$upscope $end
$enddefinitions $end
#0
$dumpvars
b0 +
b0 *
0)
b1 (
b0 '
1&
b1 %
b0 $
b0 #
1"
0!
$end
#20
b10 %
b10 (
b1 '
b1 *
b1 #
b1 $
#40
b100 %
b100 (
b10 '
b10 *
b10 #
b10 $
#60
1!
b1000 %
b1000 (
b11 '
b11 *
b11 #
b11 $
#80
0!
0&
b0 (
b10000 %
b1 +
1)
b0 '
b0 *
b100 #
b100 $
#100
1!
b100000 %
b10 +
b1 '
b1 *
b101 #
b101 $
#120
b1000000 %
b100 +
b10 '
b10 *
b110 #
b110 $
#140
b10000000 %
b1000 +
b11 '
b11 *
b111 #
b111 $
