week2/q4.v
module q4(a,b,c,d,f);
input a,b,c,d;
output f;
assign f = (~b | c | d) & (a | ~b | ~c ) & ( ~a | b | ~d) & ( ~a | b | ~c);
endmodule

week2/q4_tb.v
`timescale 1ns/1ns
`include "q4.v"

module q4_tb();
reg a,b,c,d;
wire f;

q4 l2(a,b,c,d,f);
initial
begin

  $dumpfile("q4_tb.vcd");
  $dumpvars(0, q4_tb);
  
  a=1'b0; b=1'b0; c=1'b0; d=1'b0;
  #20;
  
  a=1'b0; b=1'b0; c=1'b0; d=1'b1;
  #20;
  
  a=1'b0; b=1'b0; c=1'b1; d=1'b0;
  #20;
  
  a=1'b0; b=1'b0; c=1'b1; d=1'b1;
  #20;
  
  a=1'b0; b=1'b1; c=1'b0; d=1'b0;
  #20;
  
  a=1'b0; b=1'b1; c=1'b0; d=1'b1;
  #20;
  
  a=1'b0; b=1'b1; c=1'b1; d=1'b0;
  #20;
  
  a=1'b0; b=1'b1; c=1'b1; d=1'b1;
  #20;
  
  a=1'b0; b=1'b0; c=1'b0; d=1'b0;
  #20;
  
  a=1'b0; b=1'b0; c=1'b0; d=1'b1;
  #20;
  
  a=1'b0; b=1'b0; c=1'b1; d=1'b0;
  #20;
  
  a=1'b0; b=1'b0; c=1'b1; d=1'b1;
  #20;
  
  a=1'b1; b=1'b1; c=1'b0; d=1'b0;
  #20;
  
  a=1'b1; b=1'b1; c=1'b0; d=1'b1;
  #20;
  
  a=1'b1; b=1'b1; c=1'b1; d=1'b0;
  #20;
  
  a=1'b1; b=1'b1; c=1'b1; d=1'b1;
  #20;
  
 a=1'b1; b=1'b0; c=1'b0; d=1'b0;
  #20;
  
  a=1'b1; b=1'b0; c=1'b0; d=1'b1;
  #20;
  
  a=1'b1; b=1'b0; c=1'b1; d=1'b0;
  #20;
  
  a=1'b1; b=1'b0; c=1'b1; d=1'b1;
  #20;
  
 
  
 
 
  
  $display("test complete");
end 

endmodule

week2/q4_tb.vcd
$date
	Mon Aug 29 10:19:41 2022
$end
$version
	Icarus Verilog
$end
$timescale
	1ns
$end
$scope module q4_tb $end
$var wire 1 ! f $end
$var reg 1 " a $end
$var reg 1 # b $end
$var reg 1 $ c $end
$var reg 1 % d $end
$scope module l2 $end
$var wire 1 " a $end
$var wire 1 # b $end
$var wire 1 $ c $end
$var wire 1 % d $end
$var wire 1 ! f $end
$upscope $end
$upscope $end
$enddefinitions $end
#0
$dumpvars
0%
0$
0#
0"
1!
$end
#20
1%
#40
0%
1$
#60
1%
#80
0%
0$
1#
#100
1%
#120
0!
0%
1$
#140
1%
#160
1!
0%
0$
0#
#180
1%
#200
0%
1$
#220
1%
#240
0!
0%
0$
1#
1"
#260
1!
1%
#280
0%
1$
#300
1%
#320
0!
0%
0$
0#
#340
1%
#360
0%
1$
#380
1%
