week4/q1fa.v
module q1fa(c_in, x, y, sum, c_out);
    input c_in, x, y;
    output sum, c_out;
    assign sum = c_in ^ x ^ y;
    assign c_out = (x & y) | (y & c_in) | (c_in & x);
endmodule

week4/q1fa_tb.v
`timescale 1ns/1ns
`include "q1fa.v"

module q1fa_tb();
reg c_in,x,y;
wire sum, c_out;

q1fa l4(c_in,x,y,sum, c_out);
initial
begin

  $dumpfile("q1fa_tb.vcd");
  $dumpvars(0, q1fa_tb);
  
  x=1'b0; y=1'b0; c_in=1'b0;
  #20;
  
  x=1'b0; y=1'b0; c_in=1'b1;
  #20;
  
  x=1'b0; y=1'b1; c_in=1'b0;
  #20;
  
  x=1'b0; y=1'b1; c_in=1'b1;
  #20;
  
  x=1'b1; y=1'b0; c_in=1'b0; 
  #20;

  x=1'b1; y=1'b0; c_in=1'b1;
  #20;
  
  x=1'b1; y=1'b1; c_in=1'b0;
  #20;
  
  x=1'b1; y=1'b1; c_in=1'b1;
  #20;
   $display("test complete");
end 

endmodule

week4/q1fa_tb.vcd
$date
	Mon Sep 12 10:03:06 2022
$end
$version
	Icarus Verilog
$end
$timescale
	1ns
$end
$scope module q1fa_tb $end
$var wire 1 ! sum $end
$var wire 1 " c_out $end
$var reg 1 # c_in $end
$var reg 1 $ x $end
$var reg 1 % y $end
$scope module l4 $end
$var wire 1 # c_in $end
$var wire 1 " c_out $end
$var wire 1 ! sum $end
$var wire 1 $ x $end
$var wire 1 % y $end
$upscope $end
$upscope $end
$enddefinitions $end
#0
$dumpvars
0%
0$
0#
0"
0!
$end
#20
1!
1#
#40
1!
0#
1%
#60
1"
0!
1#
#80
0"
1!
0#
0%
1$
#100
0!
1"
1#
#120
0!
0#
1%
#140
1!
1#
