week3/q2.v
 module q2(a,b,c,d,f);
input a,b,c,d;
output f;
nor(g1, b, d);
nor(g2, a, c, ~d);
nor(g3, b, c);
nor(h, g1, g2, g3);
not(f, h);
endmodule

week3/q2_tb.v
`timescale 1ns/1ns
`include "q2.v"

module q2_tb();
reg a,b,c,d;
wire f;

q2 l3(a,b,c,d,f);
initial
begin

  $dumpfile("q2_tb.vcd");
  $dumpvars(0, q2_tb);
  
  a=1'b0; b=1'b0; c=1'b0; d=1'b0;
  #20;
  
  a=1'b0; b=1'b0; c=1'b0; d=1'b1;
  #20;
  
  a=1'b0; b=1'b0; c=1'b1; d=1'b0;
  #20;
  
  a=1'b0; b=1'b0; c=1'b1; d=1'b1;
  #20;
  
  a=1'b0; b=1'b1; c=1'b0; d=1'b0;
  #20;
  
  a=1'b0; b=1'b1; c=1'b0; d=1'b1;
  #20;
  
  a=1'b0; b=1'b1; c=1'b1; d=1'b0;
  #20;
  
  a=1'b0; b=1'b1; c=1'b1; d=1'b1;
  #20;
  
  a=1'b0; b=1'b0; c=1'b0; d=1'b0;
  #20;
  
  a=1'b0; b=1'b0; c=1'b0; d=1'b1;
  #20;
  
  a=1'b0; b=1'b0; c=1'b1; d=1'b0;
  #20;
  
  a=1'b0; b=1'b0; c=1'b1; d=1'b1;
  #20;
  
  a=1'b1; b=1'b1; c=1'b0; d=1'b0;
  #20;
  
  a=1'b1; b=1'b1; c=1'b0; d=1'b1;
  #20;
  
  a=1'b1; b=1'b1; c=1'b1; d=1'b0;
  #20;
  
  a=1'b1; b=1'b1; c=1'b1; d=1'b1;
  #20;
  
 a=1'b1; b=1'b0; c=1'b0; d=1'b0;
  #20;
  
  a=1'b1; b=1'b0; c=1'b0; d=1'b1;
  #20;
  
  a=1'b1; b=1'b0; c=1'b1; d=1'b0;
  #20;
  
  a=1'b1; b=1'b0; c=1'b1; d=1'b1;
  #20;
  
 
  
 
 
  
  $display("test complete");
end 

endmodule

week3/q2_tb.vcd
$date
	Mon Sep  5 10:19:19 2022
$end
$version
	Icarus Verilog
$end
$timescale
	1ns
$end
$scope module q2_tb $end
$var wire 1 ! f $end
$var reg 1 " a $end
$var reg 1 # b $end
$var reg 1 $ c $end
$var reg 1 % d $end
$scope module l3 $end
$var wire 1 " a $end
$var wire 1 # b $end
$var wire 1 $ c $end
$var wire 1 % d $end
$var wire 1 ! f $end
$var wire 1 & g1 $end
$var wire 1 ' g2 $end
$var wire 1 ( g3 $end
$var wire 1 ) h $end
$upscope $end
$upscope $end
$enddefinitions $end
#0
$dumpvars
0)
1(
0'
1&
0%
0$
0#
0"
1!
$end
#20
1'
0&
1%
#40
1&
0'
0(
0%
1$
#60
0!
1)
0&
1%
#80
0!
1)
0'
0%
0$
1#
#100
1!
0)
1'
1%
#120
0!
1)
0'
0%
1$
#140
1%
#160
1!
0)
0'
1&
1(
0%
0$
0#
#180
1'
0&
1%
#200
1&
0'
0(
0%
1$
#220
0!
1)
0&
1%
#240
0%
0$
1#
1"
#260
1%
#280
0%
1$
#300
1%
#320
1!
0)
1&
1(
0%
0$
0#
#340
0&
1%
#360
1&
0(
0%
1$
#380
0!
1)
0&
1%
