week3/q3.v
module q3(a,b,c,d,f);
input a,b,c,d;
output f;
//assign f = (~B & ~D) | (~A & ~C & D) | (~B & ~C);
    nor(g1, b, d);
    nor(g2, a, c, ~d);
    nor(g3, b, c);
    nor(h, g1, g2, g3);
    not(f, h);
endmodule

week3/q3_tb.v
`timescale 1ns/1ns
`include "q3.v"

module q3_tb();
reg a,b,c,d;
wire f;

q3 l2(a,b,c,d,f);
initial
begin

  $dumpfile("q3_tb.vcd");
  $dumpvars(0, q3_tb);
  
  a=1'b0; b=1'b0; c=1'b0; d=1'b0;
  #20;
  
  a=1'b0; b=1'b0; c=1'b0; d=1'b0;
  #20;
  
  a=1'b0; b=1'b0; c=1'b0; d=1'b1;
  #20;
  
  a=1'b0; b=1'b0; c=1'b0; d=1'b1;
  #20;
  
  a=1'b0; b=1'b0; c=1'b1; d=1'b0;
  #20;
  
  a=1'b0; b=1'b0; c=1'b1; d=1'b0;
  #20;
  
  a=1'b0; b=1'b0; c=1'b1; d=1'b1;
  #20;
  
  a=1'b0; b=1'b0; c=1'b1; d=1'b1;
  #20;
  
  a=1'b0; b=1'b1; c=1'b0; d=1'b0;
  #20;
  
  a=1'b0; b=1'b1; c=1'b0; d=1'b0;
  #20;
  
  a=1'b0; b=1'b1; c=1'b0; d=1'b1;
  #20;
  
  a=1'b0; b=1'b1; c=1'b0; d=1'b1;
  #20;
  
  a=1'b0; b=1'b1; c=1'b1; d=1'b0;
  #20;
  
  a=1'b0; b=1'b1; c=1'b1; d=1'b0;
  #20;
  
  a=1'b0; b=1'b1; c=1'b1; d=1'b1;
  #20;
  
  a=1'b0; b=1'b1; c=1'b1; d=1'b1;
  #20;
  
 a=1'b1; b=1'b0; c=1'b0; d=1'b0;
  #20;
  
  a=1'b1; b=1'b0; c=1'b0; d=1'b0;
  #20;
  
  a=1'b1; b=1'b0; c=1'b0; d=1'b1;
  #20;
  
  a=1'b1; b=1'b0; c=1'b0; d=1'b1;
  #20;
  
  a=1'b1; b=1'b0; c=1'b1; d=1'b0;
  #20;
  
  a=1'b1; b=1'b0; c=1'b1; d=1'b0;
  #20;
  
  a=1'b1; b=1'b0; c=1'b1; d=1'b1;
  #20;
  
  a=1'b1; b=1'b0; c=1'b1; d=1'b1;
  #20;
  
  a=1'b1; b=1'b1; c=1'b0; d=1'b0;
  #20;
  
  a=1'b1; b=1'b1; c=1'b0; d=1'b0;
  #20;
  
  a=1'b1; b=1'b1; c=1'b0; d=1'b1;
  #20;
  
  a=1'b1; b=1'b1; c=1'b0; d=1'b1;
  #20;
  
  a=1'b1; b=1'b1; c=1'b1; d=1'b0;
  #20;
  
  a=1'b1; b=1'b1; c=1'b1; d=1'b0;
  #20;
  
  a=1'b1; b=1'b1; c=1'b1; d=1'b1;
  #20;
  
 a=1'b1; b=1'b1; c=1'b1; d=1'b1;
  #20;
  
  
  
 
  
 
 
  
  $display("test complete");
end 

endmodule

week3/q3_tb.vcd
$date
	Mon Sep  5 11:12:34 2022
$end
$version
	Icarus Verilog
$end
$timescale
	1ns
$end
$scope module q3_tb $end
$var wire 1 ! f $end
$var reg 1 " a $end
$var reg 1 # b $end
$var reg 1 $ c $end
$var reg 1 % d $end
$scope module l2 $end
$var wire 1 " a $end
$var wire 1 # b $end
$var wire 1 $ c $end
$var wire 1 % d $end
$var wire 1 ! f $end
$var wire 1 & g1 $end
$var wire 1 ' g2 $end
$var wire 1 ( g3 $end
$var wire 1 ) h $end
$upscope $end
$upscope $end
$enddefinitions $end
#0
$dumpvars
0)
1(
0'
1&
0%
0$
0#
0"
1!
$end
#40
1'
0&
1%
#80
1&
0'
0(
0%
1$
#120
0!
1)
0&
1%
#160
0!
1)
0'
0%
0$
1#
#200
1!
0)
1'
1%
#240
0!
1)
0'
0%
1$
#280
1%
#320
1!
0)
1&
1(
0%
0$
0#
1"
#360
0&
1%
#400
1&
0(
0%
1$
#440
0!
1)
0&
1%
#480
0%
0$
1#
#520
1%
#560
0%
1$
#600
1%
