week8/q1.v
module dec2to4(D,En,Y);
	input [1:0]D;
	input En;
	output [0:3]Y;
	wire [2:0]i;
	reg [0:3]Y;
	
	assign i={En,D};
	always@(D or En)
	begin
		if(i==3'b100)
			Y=4'b1000;
		else if(i==3'b101)
			Y=4'b0100;
		else if(i==3'b110)
			Y=4'b0010;
		else if(i==3'b111)
			Y=4'b0001;
		else
			Y=4'b0000;
	end
endmodule

module q1(D,En,Y);
	input [2:0]D;
	input En;
	output [0:7]Y;
	wire g,h,i;
	assign g=~D[2];
	assign h=g&En;
	assign i=D[2]&En;
	dec2to4 stage0(D[1:0],h,Y[0:3]);
	dec2to4 stage1(D[1:0],i,Y[4:7]);
endmodule

week8/q1_tb.v
`timescale 1ns/1ns
`include "q1.v"

module q1_tb();
reg [2:0]D;
reg En;
wire [0:7]Y;

q1 ex1(D,En,Y);
initial
begin
	$dumpfile("q1_tb.vcd");
	$dumpvars(0,q1_tb);
	D=3'b000;En=1'b1; 
	#20;
	
	D=3'b001;En=1'b1; 
	#20;
	
	D=3'b010;En=1'b1; 
	#20;
	
	D=3'b011;En=1'b1; 
	#20;
	
	D=3'b100;En=1'b1; 
	#20;
	
	D=3'b101;En=1'b1;
	#20;
	
	D=3'b110;En=1'b1;
	#20;
	
	D=3'b111;En=1'b1;
	#20;
	
	D=3'b111;En=1'b0;
	#20;
	
	$display("Test complete");
end
endmodule

week8/q1_tb.vcd
$date
	Mon Oct 17 10:41:39 2022
$end
$version
	Icarus Verilog
$end
$timescale
	1ns
$end
$scope module q1_tb $end
$var wire 8 ! Y [0:7] $end
$var reg 3 " D [2:0] $end
$var reg 1 # En $end
$scope module ex1 $end
$var wire 3 $ D [2:0] $end
$var wire 1 # En $end
$var wire 1 % g $end
$var wire 1 & h $end
$var wire 1 ' i $end
$var wire 8 ( Y [0:7] $end
$scope module stage0 $end
$var wire 2 ) D [1:0] $end
$var wire 1 & En $end
$var wire 3 * i [2:0] $end
$var reg 4 + Y [0:3] $end
$upscope $end
$scope module stage1 $end
$var wire 2 , D [1:0] $end
$var wire 1 ' En $end
$var wire 3 - i [2:0] $end
$var reg 4 . Y [0:3] $end
$upscope $end
$upscope $end
$upscope $end
$enddefinitions $end
#0
$dumpvars
b0 .
b0 -
b0 ,
b1000 +
b100 *
b0 )
b10000000 (
0'
1&
1%
b0 $
1#
b0 "
b10000000 !
$end
#20
b1000000 !
b1000000 (
b100 +
b101 *
b1 )
b1 -
b1 ,
b1 "
b1 $
#40
b100000 !
b100000 (
b10 +
b110 *
b10 )
b10 -
b10 ,
b10 "
b10 $
#60
b10000 !
b10000 (
b1 +
b111 *
b11 )
b11 -
b11 ,
b11 "
b11 $
#80
0&
b1000 .
0%
1'
b1000 !
b1000 (
b0 +
b0 *
b0 )
b100 -
b0 ,
b100 "
b100 $
#100
b100 !
b100 (
b100 .
b1 *
b1 )
b101 -
b1 ,
b101 "
b101 $
#120
b10 !
b10 (
b10 .
b10 *
b10 )
b110 -
b10 ,
b110 "
b110 $
#140
b1 !
b1 (
b1 .
b11 *
b11 )
b111 -
b11 ,
b111 "
b111 $
#160
b0 !
b0 (
b0 .
b11 -
0'
0#
