week8/q2.v
module dec3to8(D,En,Y);
	input [2:0]D;
	input En;
	output reg [0:7]Y;
	integer i;
	always@(D or En)
	begin
		for(i=0;i<=7;i=i+1)
		begin
			if(D==i&&En==1'b1)
				Y[i]=1'b1;
			else
				Y[i]=1'b0;
		end
	end
endmodule

module q2(D,En,Y);
	input [3:0]D;
	input En;
	output [0:15]Y;
	wire g,h;
	assign g=~D[3]&En;
	assign h=D[3]&En;
	
	dec3to8 stage0(D[2:0],g,Y[0:7]);
	dec3to8 stage1(D[2:0],h,Y[8:15]);
endmodule

week8/q2_tb.v
`timescale 1ns/1ns
`include "q2.v"

module q2_tb();
reg [3:0]D;
reg En;
wire [0:15]Y;

q2 ex1(D,En,Y);
initial
begin
	$dumpfile("q2_tb.vcd");
	$dumpvars(0,q2_tb);
	D=0;En=1'b1; 
	#20;
	
	D=1;En=1'b1; 
	#20;
	
	D=2;En=1'b1; 
	#20;
	
	D=3;En=1'b1; 
	#20;
	
	D=4;En=1'b1; 
	#20;
	
	D=5;En=1'b1;
	#20;
	
	D=6;En=1'b1;
	#20;
	
	D=7;En=1'b1;
	#20;
	
	D=8;En=1'b1; 
	#20;
	
	D=9;En=1'b1; 
	#20;
	
	D=10;En=1'b1; 
	#20;
	
	D=11;En=1'b1; 
	#20;
	
	D=12;En=1'b1; 
	#20;
	
	D=13;En=1'b1;
	#20;
	
	D=14;En=1'b1;
	#20;
	
	D=15;En=1'b1;
	#20;
	
	D=15;En=1'b0;
	#20;
	
	$display("Test complete");
end
endmodule

week8/q2_tb.vcd
$date
	Mon Oct 17 10:55:58 2022
$end
$version
	Icarus Verilog
$end
$timescale
	1ns
$end
$scope module q2_tb $end
$var wire 16 ! Y [0:15] $end
$var reg 4 " D [3:0] $end
$var reg 1 # En $end
$scope module ex1 $end
$var wire 4 $ D [3:0] $end
$var wire 1 # En $end
$var wire 1 % g $end
$var wire 1 & h $end
$var wire 16 ' Y [0:15] $end
$scope module stage0 $end
$var wire 3 ( D [2:0] $end
$var wire 1 % En $end
$var reg 8 ) Y [0:7] $end
$var integer 32 * i [31:0] $end
$upscope $end
$scope module stage1 $end
$var wire 3 + D [2:0] $end
$var wire 1 & En $end
$var reg 8 , Y [0:7] $end
$var integer 32 - i [31:0] $end
$upscope $end
$upscope $end
$upscope $end
$enddefinitions $end
#0
$dumpvars
b1000 -
b0 ,
b0 +
b1000 *
b10000000 )
b0 (
b1000000000000000 '
0&
1%
b0 $
1#
b0 "
b1000000000000000 !
$end
#20
b100000000000000 !
b100000000000000 '
b1000000 )
b1000 *
b1000 -
b1 (
b1 +
b1 "
b1 $
#40
b10000000000000 !
b10000000000000 '
b100000 )
b1000 *
b1000 -
b10 (
b10 +
b10 "
b10 $
#60
b1000000000000 !
b1000000000000 '
b10000 )
b1000 *
b1000 -
b11 (
b11 +
b11 "
b11 $
#80
b100000000000 !
b100000000000 '
b1000 )
b1000 *
b1000 -
b100 (
b100 +
b100 "
b100 $
#100
b10000000000 !
b10000000000 '
b100 )
b1000 *
b1000 -
b101 (
b101 +
b101 "
b101 $
#120
b1000000000 !
b1000000000 '
b10 )
b1000 *
b1000 -
b110 (
b110 +
b110 "
b110 $
#140
b100000000 !
b100000000 '
b1 )
b1000 *
b1000 -
b111 (
b111 +
b111 "
b111 $
#160
0%
b10000000 ,
1&
b10000000 !
b10000000 '
b0 )
b1000 *
b1000 -
b0 (
b0 +
b1000 "
b1000 $
#180
b1000 *
b1000000 !
b1000000 '
b1000000 ,
b1000 -
b1 (
b1 +
b1001 "
b1001 $
#200
b1000 *
b100000 !
b100000 '
b100000 ,
b1000 -
b10 (
b10 +
b1010 "
b1010 $
#220
b1000 *
b10000 !
b10000 '
b10000 ,
b1000 -
b11 (
b11 +
b1011 "
b1011 $
#240
b1000 *
b1000 !
b1000 '
b1000 ,
b1000 -
b100 (
b100 +
b1100 "
b1100 $
#260
b1000 *
b100 !
b100 '
b100 ,
b1000 -
b101 (
b101 +
b1101 "
b1101 $
#280
b1000 *
b10 !
b10 '
b10 ,
b1000 -
b110 (
b110 +
b1110 "
b1110 $
#300
b1000 *
b1 !
b1 '
b1 ,
b1000 -
b111 (
b111 +
b1111 "
b1111 $
#320
b0 !
b0 '
b0 ,
b1000 -
0&
0#
