week8/q3.v
module dec2to4(D,En,Y);
	input [1:0]D;
	input En;
	output reg [0:3]Y;
	always@(D,En)
	begin
		case({En,D})
			3'b100:Y=4'b0111;
			3'b101:Y=4'b1011;
			3'b110:Y=4'b1101;
			3'b111:Y=4'b1110;
			default:Y=4'b1111;
		endcase
	end
endmodule

module q3(D,En,Y);
	input [3:0]D;
	input En;
	output [0:15]Y;
	wire [0:3]M;
	dec2to4 stage0(D[3:2],En,M);
	dec2to4 stage1(D[1:0],~M[0],Y[0:3]);
	dec2to4 stage2(D[1:0],~M[1],Y[4:7]);
	dec2to4 stage3(D[1:0],~M[2],Y[8:11]);
	dec2to4 stage4(D[1:0],~M[3],Y[12:15]);
endmodule

week8/q3_tb.v
`timescale 1ns/1ns
`include "q3.v"

module q3_tb();
reg [3:0]D;
reg En;
wire [0:15]Y;

q3 ex1(D,En,Y);
initial
begin
	$dumpfile("q3_tb.vcd");
	$dumpvars(0,q3_tb);
	D=0;En=1'b1; 
	#20;
	
	D=1;En=1'b1; 
	#20;
	
	D=2;En=1'b1; 
	#20;
	
	D=3;En=1'b1; 
	#20;
	
	D=4;En=1'b1; 
	#20;
	
	D=5;En=1'b1;
	#20;
	
	D=6;En=1'b1;
	#20;
	
	D=7;En=1'b1;
	#20;
	
	D=8;En=1'b1; 
	#20;
	
	D=9;En=1'b1; 
	#20;
	
	D=10;En=1'b1; 
	#20;
	
	D=11;En=1'b1; 
	#20;
	
	D=12;En=1'b1; 
	#20;
	
	D=13;En=1'b1;
	#20;
	
	D=14;En=1'b1;
	#20;
	
	D=15;En=1'b1;
	#20;
	
	D=15;En=1'b0;
	#20;
	
	$display("Test complete");
end
endmodule

week8/q3_tb.vcd
$date
	Mon Oct 17 11:07:43 2022
$end
$version
	Icarus Verilog
$end
$timescale
	1ns
$end
$scope module q3_tb $end
$var wire 16 ! Y [0:15] $end
$var reg 4 " D [3:0] $end
$var reg 1 # En $end
$scope module ex1 $end
$var wire 4 $ D [3:0] $end
$var wire 1 # En $end
$var wire 16 % Y [0:15] $end
$var wire 4 & M [0:3] $end
$scope module stage0 $end
$var wire 2 ' D [1:0] $end
$var wire 1 # En $end
$var reg 4 ( Y [0:3] $end
$upscope $end
$scope module stage1 $end
$var wire 2 ) D [1:0] $end
$var wire 1 * En $end
$var reg 4 + Y [0:3] $end
$upscope $end
$scope module stage2 $end
$var wire 2 , D [1:0] $end
$var wire 1 - En $end
$var reg 4 . Y [0:3] $end
$upscope $end
$scope module stage3 $end
$var wire 2 / D [1:0] $end
$var wire 1 0 En $end
$var reg 4 1 Y [0:3] $end
$upscope $end
$scope module stage4 $end
$var wire 2 2 D [1:0] $end
$var wire 1 3 En $end
$var reg 4 4 Y [0:3] $end
$upscope $end
$upscope $end
$upscope $end
$enddefinitions $end
#0
$dumpvars
b1111 4
03
b0 2
b1111 1
00
b0 /
b1111 .
0-
b0 ,
b111 +
1*
b0 )
b111 (
b0 '
b111 &
b111111111111111 %
b0 $
1#
b0 "
b111111111111111 !
$end
#20
b1011111111111111 !
b1011111111111111 %
b1011 +
b1 )
b1 ,
b1 /
b1 2
b1 "
b1 $
#40
b1101111111111111 !
b1101111111111111 %
b1101 +
b10 )
b10 ,
b10 /
b10 2
b10 "
b10 $
#60
b1110111111111111 !
b1110111111111111 %
b1110 +
b11 )
b11 ,
b11 /
b11 2
b11 "
b11 $
#80
b111 .
1-
0*
b1011 &
b1011 (
b1111011111111111 !
b1111011111111111 %
b1111 +
b1 '
b0 )
b0 ,
b0 /
b0 2
b100 "
b100 $
#100
b1111101111111111 !
b1111101111111111 %
b1011 .
b1 )
b1 ,
b1 /
b1 2
b101 "
b101 $
#120
b1111110111111111 !
b1111110111111111 %
b1101 .
b10 )
b10 ,
b10 /
b10 2
b110 "
b110 $
#140
b1111111011111111 !
b1111111011111111 %
b1110 .
b11 )
b11 ,
b11 /
b11 2
b111 "
b111 $
#160
b111 1
10
0-
b1101 &
b1101 (
b1111111101111111 !
b1111111101111111 %
b1111 .
b10 '
b0 )
b0 ,
b0 /
b0 2
b1000 "
b1000 $
#180
b1111111110111111 !
b1111111110111111 %
b1011 1
b1 )
b1 ,
b1 /
b1 2
b1001 "
b1001 $
#200
b1111111111011111 !
b1111111111011111 %
b1101 1
b10 )
b10 ,
b10 /
b10 2
b1010 "
b1010 $
#220
b1111111111101111 !
b1111111111101111 %
b1110 1
b11 )
b11 ,
b11 /
b11 2
b1011 "
b1011 $
#240
b111 4
13
00
b1110 &
b1110 (
b1111111111110111 !
b1111111111110111 %
b1111 1
b11 '
b0 )
b0 ,
b0 /
b0 2
b1100 "
b1100 $
#260
b1111111111111011 !
b1111111111111011 %
b1011 4
b1 )
b1 ,
b1 /
b1 2
b1101 "
b1101 $
#280
b1111111111111101 !
b1111111111111101 %
b1101 4
b10 )
b10 ,
b10 /
b10 2
b1110 "
b1110 $
#300
b1111111111111110 !
b1111111111111110 %
b1110 4
b11 )
b11 ,
b11 /
b11 2
b1111 "
b1111 $
#320
b1111111111111111 !
b1111111111111111 %
b1111 4
03
b1111 &
b1111 (
0#
